{"repJustic": {"id": "repJustic", "name": "Reproductive Justice", "orgs": [{"name": "The Jane Doe Fund", "id": "5173367843"}]}, "sVil": {"id": "sVil", "name": "Sexual & Domestic Violence", "orgs": [{"name": "SafeHouse Center", "id": "7349955444"}, {"name": "Survivor Strong", "id": "NA-SuSt"}, {"name": "Women's Center of Greater Lansing", "id": "5173729163"}]}, "envProtection": {"id": "envProtection", "name": "Environmental Protction", "orgs": [{"name": "test", "id": "_test"}]}, "artsExpr": {"id": "artsExpr", "name": "Arts & Creative Expression", "orgs": [{"name": "test", "id": "_test"}]}, "cjReform": {"id": "cjReform", "name": "Criminal Justice Reform", "orgs": [{"name": "test", "id": "_test"}]}, "mhAwareness": {"id": "mhAwareness", "name": "Mental Health Awareness", "orgs": [{"name": "test", "id": "_test"}]}, "immAccess": {"id": "immAccess", "name": "Immigration Access", "orgs": [{"name": "test", "id": "_test"}]}, "lgbtq": {"id": "lgbtq", "name": "Ending LGBTQ+ Discrimination", "orgs": [{"name": "test", "id": "_test"}]}}